spsdk_mcu_link/__init__.py
spsdk_mcu_link/probe.py
spsdk_mcu_link/__pyinstaller/__init__.py
spsdk_mcu_link/__pyinstaller/hook-spsdk_mcu_link.py
spsdk_mcu_link/dapper/__init__.py
spsdk_mcu_link/dapper/webix-dapper-wasm.wasm
spsdk_mcu_link/dapper/webix_dapper.py
spsdk_mcu_link/dapper/webix_dapper_wasm.py
spsdk_mcu_link-0.5.0.dist-info/LICENSE
spsdk_mcu_link-0.5.0.dist-info/METADATA
spsdk_mcu_link-0.5.0.dist-info/WHEEL
spsdk_mcu_link-0.5.0.dist-info/entry_points.txt
spsdk_mcu_link-0.5.0.dist-info/top_level.txt
spsdk_mcu_link-0.5.0.dist-info/RECORD
