Metadata-Version: 2.1
Name: spsdk_mcu_link
Version: 0.5.0
Summary: SPSDK MCU-Link. A debugger probe plugin for SPSDK supporting LPC-Link/MCU-Link from NXP.
Author: NXP
Maintainer-email: Kelnar Michal <michal.kelnar@nxp.com>
License: BSD-3-Clause
Project-URL: Homepage, https://github.com/nxp-mcuxpresso/spsdk_plugins/tree/master/mcu_link
Project-URL: Issues, https://github.com/nxp-mcuxpresso/spsdk_plugins/issues
Keywords: NXP,SPSDK,mcu-link,mculink,CMSIS-DAP
Classifier: Development Status :: 2 - Pre-Alpha
Classifier: Intended Audience :: Developers
Classifier: License :: OSI Approved :: BSD License
Classifier: Natural Language :: English
Classifier: Programming Language :: Python :: 3
Classifier: Programming Language :: Python :: 3.9
Classifier: Programming Language :: Python :: 3.10
Classifier: Programming Language :: Python :: 3.11
Classifier: Programming Language :: Python :: 3.12
Classifier: Programming Language :: Python :: 3.13
Requires-Python: >=3.9
License-File: LICENSE
Requires-Dist: wasmtime~=24.0.0
Requires-Dist: pyusb~=1.2.1
Requires-Dist: hidapi~=0.14.0.post2
Requires-Dist: libusb_package
